MANIFEST.in
__init__.py
__pkginfo__.py
entities.py
hooks.py
schema.py
setup.py
site_cubicweb.py
sobjects.py
cubicweb_trackervcs.egg-info/PKG-INFO
cubicweb_trackervcs.egg-info/SOURCES.txt
cubicweb_trackervcs.egg-info/dependency_links.txt
cubicweb_trackervcs.egg-info/not-zip-safe
cubicweb_trackervcs.egg-info/requires.txt
cubicweb_trackervcs.egg-info/top_level.txt
i18n/en.po
i18n/fr.po
migration/0.2.0_Any.py
migration/0.2.1_Any.py
migration/0.4.1_Any.py
migration/0.6.3_Any.py
migration/1.0.0_Any.py
migration/1.1.0_Any.py
migration/1.1.2_Any.py
migration/postcreate.py
test/test_trackervcs.py
views/__init__.py
views/review.py
views/vcs.py