Metadata-Version: 1.0
Name: cubicweb-trackervcs
Version: 1.4.1
Summary: vcsfile / tracker integration
Home-page: http://www.cubicweb.org/project/cubicweb-trackervcs
Author: LOGILAB S.A. (Paris, FRANCE)
Author-email: contact@logilab.fr
License: LGPL
Platform: UNKNOWN
